{
  "content": {
    "activities": [
      {
        "actual_seconds": 790.0,
        "calories": 81.5,
        "end_time": {
          "iso": "2016-04-22T20:51:15Z",
          "time_zone": {
            "name": "America/New_York",
            "offset": -240
          },
          "timestamp": 1461358275
        },
        "events": {
          "link": "/v2/users/571a71deff70d871cf660559/activities/walk__2016-04-22T203303/events"
        },
        "heart_rate": {
          "avg": 119.14936828613281,
          "max": null,
          "min": null
        },
        "id": "walk__2016-04-22T203303",
        "minutes": 18.2,
        "sealed": true,
        "stages": {
          "link": "/v2/users/571a71deff70d871cf660559/activities/walk__2016-04-22T203303/stages"
        },
        "start_time": {
          "iso": "2016-04-22T20:33:03Z",
          "time_zone": {
            "name": "America/New_York",
            "offset": -240
          },
          "timestamp": 1461357183
        },
        "state": "complete",
        "steps": 1547.0,
        "type": "walk",
        "version": 1
      },
      {
        "actual_seconds": 311.0,
        "calories": 33.70000076293945,
        "end_time": {
          "iso": "2016-04-22T21:00:58Z",
          "time_zone": {
            "name": "America/New_York",
            "offset": -240
          },
          "timestamp": 1461358858
        },
        "events": {
          "link": "/v2/users/571a71deff70d871cf660559/activities/walk__2016-04-22T205547/events"
        },
        "heart_rate": {
          "avg": 121.6527328491211,
          "max": null,
          "min": null
        },
        "id": "walk__2016-04-22T205547",
        "minutes": 5.183333333333334,
        "sealed": false,
        "stages": {
          "link": "/v2/users/571a71deff70d871cf660559/activities/walk__2016-04-22T205547/stages"
        },
        "start_time": {
          "iso": "2016-04-22T20:55:47Z",
          "time_zone": {
            "name": "America/New_York",
            "offset": -240
          },
          "timestamp": 1461358547
        },
        "state": "complete",
        "steps": 633.0,
        "type": "walk",
        "version": 1
      },
      {
        "actual_seconds": 704.0,
        "calories": 79.5,
        "end_time": {
          "iso": "2016-04-22T21:18:00Z",
          "time_zone": {
            "name": "America/New_York",
            "offset": -240
          },
          "timestamp": 1461359880
        },
        "events": {
          "link": "/v2/users/571a71deff70d871cf660559/activities/walk__2016-04-22T210504/events"
        },
        "heart_rate": {
          "avg": 123.26988983154297,
          "max": null,
          "min": null
        },
        "id": "walk__2016-04-22T210504",
        "minutes": 12.933333333333334,
        "sealed": true,
        "stages": {
          "link": "/v2/users/571a71deff70d871cf660559/activities/walk__2016-04-22T210504/stages"
        },
        "start_time": {
          "iso": "2016-04-22T21:05:04Z",
          "time_zone": {
            "name": "America/New_York",
            "offset": -240
          },
          "timestamp": 1461359104
        },
        "state": "complete",
        "steps": 1470.0,
        "type": "walk",
        "version": 1
      },
      {
        "actual_seconds": 456.0,
        "calories": 49.79999923706055,
        "end_time": {
          "iso": "2016-04-22T23:49:03Z",
          "time_zone": {
            "name": "America/New_York",
            "offset": -240
          },
          "timestamp": 1461368943
        },
        "events": {
          "link": "/v2/users/571a71deff70d871cf660559/activities/walk__2016-04-22T233850/events"
        },
        "heart_rate": {
          "avg": 122.14473724365234,
          "max": null,
          "min": null
        },
        "id": "walk__2016-04-22T233850",
        "minutes": 10.216666666666667,
        "sealed": true,
        "stages": {
          "link": "/v2/users/571a71deff70d871cf660559/activities/walk__2016-04-22T233850/stages"
        },
        "start_time": {
          "iso": "2016-04-22T23:38:50Z",
          "time_zone": {
            "name": "America/New_York",
            "offset": -240
          },
          "timestamp": 1461368330
        },
        "state": "complete",
        "steps": 943.0,
        "type": "walk",
        "version": 1
      },
      {
        "actual_seconds": 574.0,
        "calories": 64.30000305175781,
        "end_time": {
          "iso": "2016-04-23T00:09:25Z",
          "time_zone": {
            "name": "America/New_York",
            "offset": -240
          },
          "timestamp": 1461370165
        },
        "events": {
          "link": "/v2/users/571a71deff70d871cf660559/activities/walk__2016-04-22T235739/events"
        },
        "heart_rate": {
          "avg": 127.09233093261719,
          "max": null,
          "min": null
        },
        "id": "walk__2016-04-22T235739",
        "minutes": 11.766666666666667,
        "sealed": true,
        "stages": {
          "link": "/v2/users/571a71deff70d871cf660559/activities/walk__2016-04-22T235739/stages"
        },
        "start_time": {
          "iso": "2016-04-22T23:57:39Z",
          "time_zone": {
            "name": "America/New_York",
            "offset": -240
          },
          "timestamp": 1461369459
        },
        "state": "complete",
        "steps": 1087.0,
        "type": "walk",
        "version": 1
      },
      {
        "actual_seconds": 656.0,
        "calories": 66.30000305175781,
        "end_time": {
          "iso": "2016-04-23T00:49:20Z",
          "time_zone": {
            "name": "America/New_York",
            "offset": -240
          },
          "timestamp": 1461372560
        },
        "events": {
          "link": "/v2/users/571a71deff70d871cf660559/activities/walk__2016-04-23T003551/events"
        },
        "heart_rate": {
          "avg": 123.8687515258789,
          "max": null,
          "min": null
        },
        "id": "walk__2016-04-23T003551",
        "minutes": 13.483333333333333,
        "sealed": true,
        "stages": {
          "link": "/v2/users/571a71deff70d871cf660559/activities/walk__2016-04-23T003551/stages"
        },
        "start_time": {
          "iso": "2016-04-23T00:35:51Z",
          "time_zone": {
            "name": "America/New_York",
            "offset": -240
          },
          "timestamp": 1461371751
        },
        "state": "complete",
        "steps": 1283.0,
        "type": "walk",
        "version": 1
      }
    ]
  },
  "meta": {
    "response_code": 200
  }
}