{
  "content": {
    "activities": [
      {
        "actual_seconds": 22560,
        "calories": 333.364013671875,
        "date": "2016-05-01",
        "end_time": {
          "iso": "2016-05-02T10:51:21Z",
          "time_zone": {
            "name": "America/New_York",
            "offset": -240
          },
          "timestamp": 1462186281
        },
        "events": [
          {
            "time": {
              "iso": "2016-05-02T04:41:00Z",
              "time_zone": {
                "name": "America/New_York",
                "offset": -240
              },
              "timestamp": 1462164060
            },
            "type": "toss_and_turn"
          },
          {
            "time": {
              "iso": "2016-05-02T04:46:00Z",
              "time_zone": {
                "name": "America/New_York",
                "offset": -240
              },
              "timestamp": 1462164360
            },
            "type": "toss_and_turn"
          },
          {
            "time": {
              "iso": "2016-05-02T04:50:00Z",
              "time_zone": {
                "name": "America/New_York",
                "offset": -240
              },
              "timestamp": 1462164600
            },
            "type": "toss_and_turn"
          },
          {
            "time": {
              "iso": "2016-05-02T04:55:00Z",
              "time_zone": {
                "name": "America/New_York",
                "offset": -240
              },
              "timestamp": 1462164900
            },
            "type": "toss_and_turn"
          },
          {
            "time": {
              "iso": "2016-05-02T05:01:00Z",
              "time_zone": {
                "name": "America/New_York",
                "offset": -240
              },
              "timestamp": 1462165260
            },
            "type": "toss_and_turn"
          },
          {
            "time": {
              "iso": "2016-05-02T05:08:00Z",
              "time_zone": {
                "name": "America/New_York",
                "offset": -240
              },
              "timestamp": 1462165680
            },
            "type": "toss_and_turn"
          },
          {
            "time": {
              "iso": "2016-05-02T05:09:00Z",
              "time_zone": {
                "name": "America/New_York",
                "offset": -240
              },
              "timestamp": 1462165740
            },
            "type": "toss_and_turn"
          },
          {
            "time": {
              "iso": "2016-05-02T05:10:00Z",
              "time_zone": {
                "name": "America/New_York",
                "offset": -240
              },
              "timestamp": 1462165800
            },
            "type": "toss_and_turn"
          },
          {
            "time": {
              "iso": "2016-05-02T05:11:00Z",
              "time_zone": {
                "name": "America/New_York",
                "offset": -240
              },
              "timestamp": 1462165860
            },
            "type": "toss_and_turn"
          },
          {
            "time": {
              "iso": "2016-05-02T05:22:00Z",
              "time_zone": {
                "name": "America/New_York",
                "offset": -240
              },
              "timestamp": 1462166520
            },
            "type": "toss_and_turn"
          },
          {
            "time": {
              "iso": "2016-05-02T05:23:00Z",
              "time_zone": {
                "name": "America/New_York",
                "offset": -240
              },
              "timestamp": 1462166580
            },
            "type": "toss_and_turn"
          },
          {
            "time": {
              "iso": "2016-05-02T05:26:00Z",
              "time_zone": {
                "name": "America/New_York",
                "offset": -240
              },
              "timestamp": 1462166760
            },
            "type": "toss_and_turn"
          },
          {
            "time": {
              "iso": "2016-05-02T06:23:00Z",
              "time_zone": {
                "name": "America/New_York",
                "offset": -240
              },
              "timestamp": 1462170180
            },
            "type": "toss_and_turn"
          },
          {
            "time": {
              "iso": "2016-05-02T06:24:00Z",
              "time_zone": {
                "name": "America/New_York",
                "offset": -240
              },
              "timestamp": 1462170240
            },
            "type": "toss_and_turn"
          },
          {
            "time": {
              "iso": "2016-05-02T06:50:00Z",
              "time_zone": {
                "name": "America/New_York",
                "offset": -240
              },
              "timestamp": 1462171800
            },
            "type": "toss_and_turn"
          },
          {
            "time": {
              "iso": "2016-05-02T07:34:00Z",
              "time_zone": {
                "name": "America/New_York",
                "offset": -240
              },
              "timestamp": 1462174440
            },
            "type": "toss_and_turn"
          },
          {
            "time": {
              "iso": "2016-05-02T08:41:00Z",
              "time_zone": {
                "name": "America/New_York",
                "offset": -240
              },
              "timestamp": 1462178460
            },
            "type": "toss_and_turn"
          },
          {
            "time": {
              "iso": "2016-05-02T08:58:00Z",
              "time_zone": {
                "name": "America/New_York",
                "offset": -240
              },
              "timestamp": 1462179480
            },
            "type": "toss_and_turn"
          },
          {
            "time": {
              "iso": "2016-05-02T09:47:00Z",
              "time_zone": {
                "name": "America/New_York",
                "offset": -240
              },
              "timestamp": 1462182420
            },
            "type": "toss_and_turn"
          },
          {
            "time": {
              "iso": "2016-05-02T09:51:00Z",
              "time_zone": {
                "name": "America/New_York",
                "offset": -240
              },
              "timestamp": 1462182660
            },
            "type": "toss_and_turn"
          },
          {
            "time": {
              "iso": "2016-05-02T10:04:00Z",
              "time_zone": {
                "name": "America/New_York",
                "offset": -240
              },
              "timestamp": 1462183440
            },
            "type": "toss_and_turn"
          },
          {
            "time": {
              "iso": "2016-05-02T10:13:00Z",
              "time_zone": {
                "name": "America/New_York",
                "offset": -240
              },
              "timestamp": 1462183980
            },
            "type": "toss_and_turn"
          },
          {
            "time": {
              "iso": "2016-05-02T10:18:00Z",
              "time_zone": {
                "name": "America/New_York",
                "offset": -240
              },
              "timestamp": 1462184280
            },
            "type": "toss_and_turn"
          },
          {
            "time": {
              "iso": "2016-05-02T10:30:00Z",
              "time_zone": {
                "name": "America/New_York",
                "offset": -240
              },
              "timestamp": 1462185000
            },
            "type": "toss_and_turn"
          },
          {
            "time": {
              "iso": "2016-05-02T10:35:00Z",
              "time_zone": {
                "name": "America/New_York",
                "offset": -240
              },
              "timestamp": 1462185300
            },
            "type": "toss_and_turn"
          },
          {
            "time": {
              "iso": "2016-05-02T10:51:00Z",
              "time_zone": {
                "name": "America/New_York",
                "offset": -240
              },
              "timestamp": 1462186260
            },
            "type": "toss_and_turn"
          }
        ],
        "heart_rate": {
          "avg": 66.95613098144531,
          "max": null,
          "min": null
        },
        "id": "sleep__2016-05-02T043521",
        "minutes": 376,
        "sealed": true,
        "sleep": {
          "deep_minutes": 105,
          "deep_percent": 28.0,
          "interruption_minutes": 0,
          "interruptions": 0,
          "light_minutes": 195,
          "light_percent": 52.0,
          "quality": 97,
          "rem_minutes": 75,
          "rem_percent": 20.0,
          "toss_and_turn": 26,
          "unknown_minutes": 0,
          "unknown_percent": 0.0
        },
        "stages": [
          {
            "end_time": {
              "iso": "2016-05-02T05:34:00Z",
              "time_zone": {
                "name": "America/New_York",
                "offset": -240
              },
              "timestamp": 1462167240
            },
            "minutes": 58,
            "start_time": {
              "iso": "2016-05-02T04:36:00Z",
              "time_zone": {
                "name": "America/New_York",
                "offset": -240
              },
              "timestamp": 1462163760
            },
            "type": "light"
          },
          {
            "end_time": {
              "iso": "2016-05-02T05:57:00Z",
              "time_zone": {
                "name": "America/New_York",
                "offset": -240
              },
              "timestamp": 1462168620
            },
            "minutes": 23,
            "start_time": {
              "iso": "2016-05-02T05:34:00Z",
              "time_zone": {
                "name": "America/New_York",
                "offset": -240
              },
              "timestamp": 1462167240
            },
            "type": "deep"
          },
          {
            "end_time": {
              "iso": "2016-05-02T06:17:00Z",
              "time_zone": {
                "name": "America/New_York",
                "offset": -240
              },
              "timestamp": 1462169820
            },
            "minutes": 20,
            "start_time": {
              "iso": "2016-05-02T05:57:00Z",
              "time_zone": {
                "name": "America/New_York",
                "offset": -240
              },
              "timestamp": 1462168620
            },
            "type": "light"
          },
          {
            "end_time": {
              "iso": "2016-05-02T06:29:00Z",
              "time_zone": {
                "name": "America/New_York",
                "offset": -240
              },
              "timestamp": 1462170540
            },
            "minutes": 12,
            "start_time": {
              "iso": "2016-05-02T06:17:00Z",
              "time_zone": {
                "name": "America/New_York",
                "offset": -240
              },
              "timestamp": 1462169820
            },
            "type": "rem"
          },
          {
            "end_time": {
              "iso": "2016-05-02T06:31:00Z",
              "time_zone": {
                "name": "America/New_York",
                "offset": -240
              },
              "timestamp": 1462170660
            },
            "minutes": 2,
            "start_time": {
              "iso": "2016-05-02T06:29:00Z",
              "time_zone": {
                "name": "America/New_York",
                "offset": -240
              },
              "timestamp": 1462170540
            },
            "type": "light"
          },
          {
            "end_time": {
              "iso": "2016-05-02T07:15:00Z",
              "time_zone": {
                "name": "America/New_York",
                "offset": -240
              },
              "timestamp": 1462173300
            },
            "minutes": 44,
            "start_time": {
              "iso": "2016-05-02T06:31:00Z",
              "time_zone": {
                "name": "America/New_York",
                "offset": -240
              },
              "timestamp": 1462170660
            },
            "type": "deep"
          },
          {
            "end_time": {
              "iso": "2016-05-02T07:17:00Z",
              "time_zone": {
                "name": "America/New_York",
                "offset": -240
              },
              "timestamp": 1462173420
            },
            "minutes": 2,
            "start_time": {
              "iso": "2016-05-02T07:15:00Z",
              "time_zone": {
                "name": "America/New_York",
                "offset": -240
              },
              "timestamp": 1462173300
            },
            "type": "light"
          },
          {
            "end_time": {
              "iso": "2016-05-02T07:33:00Z",
              "time_zone": {
                "name": "America/New_York",
                "offset": -240
              },
              "timestamp": 1462174380
            },
            "minutes": 16,
            "start_time": {
              "iso": "2016-05-02T07:17:00Z",
              "time_zone": {
                "name": "America/New_York",
                "offset": -240
              },
              "timestamp": 1462173420
            },
            "type": "rem"
          },
          {
            "end_time": {
              "iso": "2016-05-02T07:58:00Z",
              "time_zone": {
                "name": "America/New_York",
                "offset": -240
              },
              "timestamp": 1462175880
            },
            "minutes": 25,
            "start_time": {
              "iso": "2016-05-02T07:33:00Z",
              "time_zone": {
                "name": "America/New_York",
                "offset": -240
              },
              "timestamp": 1462174380
            },
            "type": "light"
          },
          {
            "end_time": {
              "iso": "2016-05-02T08:36:00Z",
              "time_zone": {
                "name": "America/New_York",
                "offset": -240
              },
              "timestamp": 1462178160
            },
            "minutes": 38,
            "start_time": {
              "iso": "2016-05-02T07:58:00Z",
              "time_zone": {
                "name": "America/New_York",
                "offset": -240
              },
              "timestamp": 1462175880
            },
            "type": "deep"
          },
          {
            "end_time": {
              "iso": "2016-05-02T09:47:00Z",
              "time_zone": {
                "name": "America/New_York",
                "offset": -240
              },
              "timestamp": 1462182420
            },
            "minutes": 71,
            "start_time": {
              "iso": "2016-05-02T08:36:00Z",
              "time_zone": {
                "name": "America/New_York",
                "offset": -240
              },
              "timestamp": 1462178160
            },
            "type": "light"
          },
          {
            "end_time": {
              "iso": "2016-05-02T10:34:00Z",
              "time_zone": {
                "name": "America/New_York",
                "offset": -240
              },
              "timestamp": 1462185240
            },
            "minutes": 47,
            "start_time": {
              "iso": "2016-05-02T09:47:00Z",
              "time_zone": {
                "name": "America/New_York",
                "offset": -240
              },
              "timestamp": 1462182420
            },
            "type": "rem"
          },
          {
            "end_time": {
              "iso": "2016-05-02T10:51:00Z",
              "time_zone": {
                "name": "America/New_York",
                "offset": -240
              },
              "timestamp": 1462186260
            },
            "minutes": 17,
            "start_time": {
              "iso": "2016-05-02T10:34:00Z",
              "time_zone": {
                "name": "America/New_York",
                "offset": -240
              },
              "timestamp": 1462185240
            },
            "type": "light"
          }
        ],
        "start_time": {
          "iso": "2016-05-02T04:35:21Z",
          "time_zone": {
            "name": "America/New_York",
            "offset": -240
          },
          "timestamp": 1462163721
        },
        "state": "complete",
        "type": "sleep",
        "version": 2
      }
    ]
  },
  "meta": {
    "response_code": 200
  }
}